{
  "code": "3W3Z6F",
  "ownerId": "615359fd-46fa-419e-a7ab-a393d413e27c",
  "ownerUsername": "DDK",
  "createdAt": 1783477157722,
  "members": [
    {
      "id": "615359fd-46fa-419e-a7ab-a393d413e27c",
      "username": "DDK",
      "joinedAt": 1783477157722,
      "lastSeen": 1783477679734
    },
    {
      "id": "797b2504-8d0d-4472-a237-e29c774e1af0",
      "username": "DDX",
      "joinedAt": 1783477188908,
      "lastSeen": 1783477681195,
      "viewOnly": false
    }
  ],
  "kicked": []
}